kofu/__init__.py
kofu/local_threaded_executor.py
kofu/store/__init__.py
kofu/store/sqlite_store.py
kofu/store/task_state.py
kofu/store/task_store.py
kofu/tasks/__init__.py
kofu/tasks/simple_fn.py
kofu/tasks/task.py
kofu-0.3.0.dist-info/METADATA
kofu-0.3.0.dist-info/WHEEL
kofu-0.3.0.dist-info/licenses/LICENSE
kofu-0.3.0.dist-info/RECORD
