Metadata-Version: 2.4
Name: kofu
Version: 0.3.0
Summary: An execution framework for i/o heavy task with memory persistence and concurrency
Project-URL: Homepage, https://github.com/avyuh/kofu
Project-URL: Issues, https://github.com/avyuh/kofu/issues
Author-email: avyuh <contact@jhaabhi.com>
License: MIT
License-File: LICENSE
Classifier: License :: OSI Approved :: MIT License
Classifier: Operating System :: OS Independent
Classifier: Programming Language :: Python :: 3
Requires-Python: >=3.10
Requires-Dist: packaging>=24.2
Requires-Dist: tqdm
Provides-Extra: dev
Requires-Dist: flake8>=6.0.0; extra == 'dev'
Requires-Dist: pytest>=6.0; extra == 'dev'
